knowledge_storm/__init__.py
knowledge_storm/dataclass.py
knowledge_storm/encoder.py
knowledge_storm/interface.py
knowledge_storm/lm.py
knowledge_storm/logging_wrapper.py
knowledge_storm/rm.py
knowledge_storm/utils.py
knowledge_storm/collaborative_storm/__init__.py
knowledge_storm/collaborative_storm/engine.py
knowledge_storm/collaborative_storm/modules/__init__.py
knowledge_storm/collaborative_storm/modules/article_generation.py
knowledge_storm/collaborative_storm/modules/callback.py
knowledge_storm/collaborative_storm/modules/co_storm_agents.py
knowledge_storm/collaborative_storm/modules/collaborative_storm_utils.py
knowledge_storm/collaborative_storm/modules/costorm_expert_utterance_generator.py
knowledge_storm/collaborative_storm/modules/expert_generation.py
knowledge_storm/collaborative_storm/modules/grounded_question_answering.py
knowledge_storm/collaborative_storm/modules/grounded_question_generation.py
knowledge_storm/collaborative_storm/modules/information_insertion_module.py
knowledge_storm/collaborative_storm/modules/knowledge_base_summary.py
knowledge_storm/collaborative_storm/modules/simulate_user.py
knowledge_storm/collaborative_storm/modules/warmstart_hierarchical_chat.py
knowledge_storm/storm_wiki/__init__.py
knowledge_storm/storm_wiki/engine.py
knowledge_storm/storm_wiki/modules/__init__.py
knowledge_storm/storm_wiki/modules/article_generation.py
knowledge_storm/storm_wiki/modules/article_polish.py
knowledge_storm/storm_wiki/modules/callback.py
knowledge_storm/storm_wiki/modules/knowledge_curation.py
knowledge_storm/storm_wiki/modules/outline_generation.py
knowledge_storm/storm_wiki/modules/persona_generator.py
knowledge_storm/storm_wiki/modules/retriever.py
knowledge_storm/storm_wiki/modules/storm_dataclass.py
knowledge_storm-1.1.1.dist-info/licenses/LICENSE
knowledge_storm-1.1.1.dist-info/METADATA
knowledge_storm-1.1.1.dist-info/WHEEL
knowledge_storm-1.1.1.dist-info/top_level.txt
knowledge_storm-1.1.1.dist-info/RECORD
