Metadata-Version: 2.4
Name: knowledge-storm
Version: 1.1.1
Summary: STORM: A language model-powered knowledge curation engine.
Home-page: https://github.com/stanford-oval/storm
Author: Yijia Shao, Yucheng Jiang
Author-email: shaoyj@stanford.edu, yuchengj@stanford.edu
License: MIT License
Classifier: Development Status :: 3 - Alpha
Classifier: License :: OSI Approved :: MIT License
Classifier: Operating System :: OS Independent
Classifier: Programming Language :: Python :: 3
Classifier: Programming Language :: Python :: 3.10
Classifier: Programming Language :: Python :: 3.11
Requires-Python: >=3.10
License-File: LICENSE
Requires-Dist: dspy_ai==2.4.9
Requires-Dist: wikipedia==1.4.0
Requires-Dist: sentence-transformers
Requires-Dist: toml
Requires-Dist: langchain-text-splitters
Requires-Dist: trafilatura
Requires-Dist: langchain-huggingface
Requires-Dist: qdrant-client
Requires-Dist: langchain-qdrant
Requires-Dist: numpy
Requires-Dist: litellm
Requires-Dist: diskcache
Dynamic: author
Dynamic: author-email
Dynamic: classifier
Dynamic: description
Dynamic: description-content-type
Dynamic: home-page
Dynamic: license
Dynamic: license-file
Dynamic: requires-dist
Dynamic: requires-python
Dynamic: summary
